lockedin_handeler/__init__.py
lockedin_handeler/convex_handler.py
lockedin_handeler-1.8.0.dist-info/licenses/LICENSE
lockedin_handeler-1.8.0.dist-info/METADATA
lockedin_handeler-1.8.0.dist-info/WHEEL
lockedin_handeler-1.8.0.dist-info/top_level.txt
lockedin_handeler-1.8.0.dist-info/RECORD
