Metadata-Version: 2.4
Name: lockedin-handeler
Version: 1.8.0
Summary: A simple Python package for managing space availability in Convex
Home-page: https://github.com/yourusername/convex-space-manager
Author: KAO
Author-email: KAO <kao@overload.studio>
Maintainer-email: KAO <kao@overload.studio>
License: MIT
Project-URL: Homepage, https://github.com/yourusername/convex-space-manager
Project-URL: Repository, https://github.com/yourusername/convex-space-manager
Project-URL: Issues, https://github.com/yourusername/convex-space-manager/issues
Keywords: convex,space,management,database,real-time
Classifier: Development Status :: 4 - Beta
Classifier: Intended Audience :: Developers
Classifier: License :: OSI Approved :: MIT License
Classifier: Operating System :: OS Independent
Classifier: Programming Language :: Python :: 3
Classifier: Programming Language :: Python :: 3.7
Classifier: Programming Language :: Python :: 3.8
Classifier: Programming Language :: Python :: 3.9
Classifier: Programming Language :: Python :: 3.10
Classifier: Programming Language :: Python :: 3.11
Classifier: Programming Language :: Python :: 3.12
Requires-Python: >=3.7
License-File: LICENSE
Requires-Dist: convex>=0.7.0
Provides-Extra: dev
Requires-Dist: pytest>=6.0; extra == "dev"
Requires-Dist: black; extra == "dev"
Requires-Dist: flake8; extra == "dev"
Dynamic: author
Dynamic: home-page
Dynamic: license-file
Dynamic: requires-python
